kring/README.md
kring/__init__.py
kring/bak__main__.py
kring/kring.so
kring/libkring.so
kring/test.py
kring-0.0.1.dist-info/METADATA
kring-0.0.1.dist-info/WHEEL
kring-0.0.1.dist-info/RECORD
